zozol
