Metadata-Version: 1.1
Name: zozol
Version: 0.2.2
Summary: Broken ASN1 for DSTU
Home-page: https://github.com/muromec/zozol
Author: Ilya Petrov
Author-email: ilya.muromec@gmail.com
License: UNKNOWN
Platform: UNKNOWN
Classifier: Programming Language :: Python
